marqo1/__init__.py
marqo1/_httprequests.py
marqo1/client.py
marqo1/cloud_helpers.py
marqo1/config.py
marqo1/default_instance_mappings.py
marqo1/defaults.py
marqo1/enums.py
marqo1/errors.py
marqo1/index.py
marqo1/instance_mappings.py
marqo1/marqo_cloud_instance_mappings.py
marqo1/marqo_logging.py
marqo1/utils.py
marqo1/version.py
marqo1/models/__init__.py
marqo1/models/create_index_settings.py
marqo1/models/search_models.py
marqo1-2.1.0.dist-info/LICENSE
marqo1-2.1.0.dist-info/METADATA
marqo1-2.1.0.dist-info/WHEEL
marqo1-2.1.0.dist-info/top_level.txt
marqo1-2.1.0.dist-info/RECORD
